qz/__init__.py
qz/qz.py
qzcli-0.1.0.dist-info/METADATA
qzcli-0.1.0.dist-info/WHEEL
qzcli-0.1.0.dist-info/entry_points.txt
qzcli-0.1.0.dist-info/top_level.txt
qzcli-0.1.0.dist-info/RECORD
