Metadata-Version: 2.4
Name: qzcli
Version: 0.1.0
Summary: CLI tool to run remote Python queries via SSH
Home-page: https://github.com/yourusername/qz
Author: Your Name
Author-email: you@example.com
Requires-Python: >=3.6
Dynamic: author
Dynamic: author-email
Dynamic: home-page
Dynamic: requires-python
Dynamic: summary
